Metadata-Version: 1.1
Name: ebaysdk
Version: 2.1.3
Summary: eBay SDK for Python
Home-page: https://github.com/timotheus/ebaysdk-python
Author: Tim Keefer
Author-email: tkeefer@gmail.com
License: COMMON DEVELOPMENT AND DISTRIBUTION LICENSE (CDDL) Version 1.0
Platform: UNKNOWN
Classifier: Topic :: Internet :: WWW/HTTP
Classifier: Intended Audience :: Developers
Provides: ebaysdk
